subgate/__init__.py
subgate/client/__init__.py
subgate/client/base_client.py
subgate/client/exceptions.py
subgate/client/plan_client.py
subgate/client/subgate_client.py
subgate/client/subscription_client.py
subgate/client/webhook_client.py
subgate/domain/__init__.py
subgate/domain/cycle.py
subgate/domain/discount.py
subgate/domain/enums.py
subgate/domain/events.py
subgate/domain/plan.py
subgate/domain/subscription.py
subgate/domain/usage.py
subgate/domain/webhook.py
subgate/services/__init__.py
subgate/services/deserializers.py
subgate/services/serializers.py
subgate/services/validators.py
subgate/utils.py
subgate-0.2.0.dist-info/METADATA
subgate-0.2.0.dist-info/WHEEL
subgate-0.2.0.dist-info/RECORD
