Metadata-Version: 2.1
Name: subgate
Version: 0.2.0
Summary: Python client for Subgate Microservice
License: MIT
Author: barmatey
Requires-Python: >=3.12,<4.0
Classifier: License :: OSI Approved :: MIT License
Classifier: Programming Language :: Python :: 3
Classifier: Programming Language :: Python :: 3.12
Classifier: Programming Language :: Python :: 3.13
Requires-Dist: httpx (>=0.28.1,<0.29.0)
